arrest/__init__.py
arrest/__main__.py
arrest/_config.py
arrest/cli/__init__.py
arrest/cli/arguments.py
arrest/common.py
arrest/converters.py
arrest/defaults.py
arrest/exceptions.py
arrest/handler.py
arrest/http.py
arrest/logging.py
arrest/openapi/__init__.py
arrest/openapi/_base.py
arrest/openapi/_config.py
arrest/openapi/init_template.py
arrest/openapi/parser.py
arrest/openapi/resource_template.py
arrest/openapi/service_template.py
arrest/openapi/spec.py
arrest/openapi/templates/__init__.jinja2
arrest/openapi/templates/resources.jinja2
arrest/openapi/templates/services.jinja2
arrest/openapi/utils.py
arrest/params.py
arrest/py.typed
arrest/resource.py
arrest/service.py
arrest/types.py
arrest/utils.py
arrest-0.1.10.dist-info/LICENSE
arrest-0.1.10.dist-info/METADATA
arrest-0.1.10.dist-info/WHEEL
arrest-0.1.10.dist-info/entry_points.txt
arrest-0.1.10.dist-info/RECORD
