Metadata-Version: 2.1
Name: arrest
Version: 0.1.10
Summary: Arrest is a wrapper of pydantic and httpx to make your REST api calls type-safe and structured
Home-page: https://s-bose.github.io/arrest
License: MIT
Keywords: arrest,rest,pydantic,httpx,api
Author: shiladitya
Author-email: shiladitya_basu@live.com
Requires-Python: >=3.10,<4.0
Classifier: Intended Audience :: Developers
Classifier: License :: OSI Approved :: MIT License
Classifier: Natural Language :: English
Classifier: Programming Language :: Python :: 3
Classifier: Programming Language :: Python :: 3.10
Classifier: Programming Language :: Python :: 3.11
Classifier: Programming Language :: Python :: 3.10
Classifier: Programming Language :: Python :: 3.11
Classifier: Topic :: Software Development :: Libraries
Provides-Extra: openapi
Requires-Dist: argcomplete (>=3.2.2,<4.0.0)
Requires-Dist: datamodel-code-generator (==0.25.8) ; extra == "openapi"
Requires-Dist: httpx (>=0.27.0,<0.28.0)
Requires-Dist: jinja2 (>=3.1.3,<4.0.0) ; extra == "openapi"
Requires-Dist: orjson (>=3.9.10,<4.0.0)
Requires-Dist: pydantic (>=1.10.15,<3.0.0)
Requires-Dist: pyyaml (>=6.0.1,<7.0.0)
Requires-Dist: tenacity (>=8.5.0,<9.0.0)
Project-URL: Documentation, https://s-bose.github.io/arrest
Project-URL: Repository, https://github.com/s-bose/arrest
Project-URL: changelog, https://s-bose.github.io/arrest/release-notes
